tvdbAPI.py
tvdbAPI-0.2.11.dist-info/LICENSE
tvdbAPI-0.2.11.dist-info/METADATA
tvdbAPI-0.2.11.dist-info/WHEEL
tvdbAPI-0.2.11.dist-info/top_level.txt
tvdbAPI-0.2.11.dist-info/RECORD
