Metadata-Version: 2.1
Name: tvdbAPI
Version: 0.2.11
Summary: Python Module for accessing the TVDB API
Home-page: https://github.com/TehRiehlDeal/TVDB-API
Author: Kevin Riehl
Author-email: kevinriehl@gmail.com
License: MIT
Classifier: Programming Language :: Python :: 3
Classifier: Operating System :: OS Independent
Requires-Python: >=3.6
License-File: LICENSE
Requires-Dist: requests (>=2.22.0)
Requires-Dist: sanction (>=0.4.1)
